{
  "annotations": { "list": [] },
  "editable": true,
  "fiscalYearStartMonth": 0,
  "graphTooltip": 1,
  "id": null,
  "links": [],
  "panels": [
    {
      "collapsed": false,
      "gridPos": { "h": 1, "w": 24, "x": 0, "y": 0 },
      "id": 100,
      "title": "Overview",
      "type": "row"
    },
    {
      "datasource": { "type": "prometheus", "uid": "PBFA97CFB590B2093" },
      "fieldConfig": {
        "defaults": {
          "color": { "mode": "thresholds" },
          "thresholds": { "mode": "absolute", "steps": [{ "color": "green", "value": null }, { "color": "yellow", "value": 200000000 }, { "color": "red", "value": 500000000 }] },
          "unit": "bytes"
        }
      },
      "gridPos": { "h": 4, "w": 6, "x": 0, "y": 1 },
      "id": 1,
      "options": { "colorMode": "value", "graphMode": "area", "reduceOptions": { "calcs": ["lastNotNull"] }, "textMode": "auto" },
      "title": "Memory (RSS)",
      "type": "stat",
      "targets": [{ "expr": "process_resident_memory_bytes{job=\"mimic\"}", "refId": "A" }]
    },
    {
      "datasource": { "type": "prometheus", "uid": "PBFA97CFB590B2093" },
      "fieldConfig": {
        "defaults": {
          "color": { "mode": "thresholds" },
          "thresholds": { "mode": "absolute", "steps": [{ "color": "green", "value": null }, { "color": "yellow", "value": 0.5 }, { "color": "red", "value": 1.0 }] },
          "unit": "percentunit",
          "decimals": 1
        }
      },
      "gridPos": { "h": 4, "w": 6, "x": 6, "y": 1 },
      "id": 2,
      "options": { "colorMode": "value", "graphMode": "area", "reduceOptions": { "calcs": ["lastNotNull"] }, "textMode": "auto" },
      "title": "CPU Rate",
      "type": "stat",
      "targets": [{ "expr": "rate(process_cpu_seconds_total{job=\"mimic\"}[1m])", "refId": "A" }]
    },
    {
      "datasource": { "type": "prometheus", "uid": "PBFA97CFB590B2093" },
      "fieldConfig": {
        "defaults": {
          "color": { "mode": "thresholds" },
          "thresholds": { "mode": "absolute", "steps": [{ "color": "green", "value": null }, { "color": "yellow", "value": 100 }, { "color": "red", "value": 500 }] }
        }
      },
      "gridPos": { "h": 4, "w": 6, "x": 12, "y": 1 },
      "id": 3,
      "options": { "colorMode": "value", "graphMode": "area", "reduceOptions": { "calcs": ["lastNotNull"] }, "textMode": "auto" },
      "title": "Open FDs",
      "type": "stat",
      "targets": [{ "expr": "process_open_fds{job=\"mimic\"}", "refId": "A" }]
    },
    {
      "datasource": { "type": "loki", "uid": "loki" },
      "fieldConfig": {
        "defaults": {
          "color": { "mode": "thresholds" },
          "thresholds": { "mode": "absolute", "steps": [{ "color": "green", "value": null }, { "color": "red", "value": 1 }] }
        }
      },
      "gridPos": { "h": 4, "w": 6, "x": 18, "y": 1 },
      "id": 4,
      "options": { "colorMode": "value", "graphMode": "area", "reduceOptions": { "calcs": ["lastNotNull"] }, "textMode": "auto" },
      "title": "Error Lines (1m)",
      "type": "stat",
      "targets": [{ "expr": "sum(count_over_time({service=\"mimic\"} |~ \"(?i)(error|exception|traceback)\" [1m])) or vector(0)", "refId": "A" }]
    },
    {
      "collapsed": false,
      "gridPos": { "h": 1, "w": 24, "x": 0, "y": 5 },
      "id": 101,
      "title": "Resource Usage",
      "type": "row"
    },
    {
      "datasource": { "type": "prometheus", "uid": "PBFA97CFB590B2093" },
      "fieldConfig": {
        "defaults": {
          "color": { "mode": "palette-classic" },
          "custom": { "drawStyle": "line", "fillOpacity": 15, "lineWidth": 2, "showPoints": "never", "spanNulls": false },
          "unit": "bytes"
        }
      },
      "gridPos": { "h": 8, "w": 12, "x": 0, "y": 6 },
      "id": 5,
      "options": { "legend": { "displayMode": "list", "placement": "bottom" }, "tooltip": { "mode": "multi", "sort": "desc" } },
      "title": "Memory Over Time",
      "type": "timeseries",
      "targets": [
        { "expr": "process_resident_memory_bytes{job=\"mimic\"}", "legendFormat": "RSS", "refId": "A" },
        { "expr": "process_virtual_memory_bytes{job=\"mimic\"}", "legendFormat": "Virtual", "refId": "B" }
      ]
    },
    {
      "datasource": { "type": "prometheus", "uid": "PBFA97CFB590B2093" },
      "fieldConfig": {
        "defaults": {
          "color": { "mode": "palette-classic" },
          "custom": { "drawStyle": "line", "fillOpacity": 15, "lineWidth": 2, "showPoints": "never", "spanNulls": false },
          "unit": "percentunit",
          "decimals": 2
        }
      },
      "gridPos": { "h": 8, "w": 12, "x": 12, "y": 6 },
      "id": 6,
      "options": { "legend": { "displayMode": "list", "placement": "bottom" }, "tooltip": { "mode": "multi", "sort": "desc" } },
      "title": "CPU Usage Over Time",
      "type": "timeseries",
      "targets": [
        { "expr": "rate(process_cpu_seconds_total{job=\"mimic\"}[1m])", "legendFormat": "CPU/sec", "refId": "A" }
      ]
    },
    {
      "collapsed": false,
      "gridPos": { "h": 1, "w": 24, "x": 0, "y": 14 },
      "id": 102,
      "title": "Logs",
      "type": "row"
    },
    {
      "datasource": { "type": "loki", "uid": "loki" },
      "gridPos": { "h": 12, "w": 24, "x": 0, "y": 15 },
      "id": 20,
      "options": {
        "showTime": true,
        "showLabels": false,
        "showCommonLabels": false,
        "wrapLogMessage": true,
        "prettifyLogMessage": false,
        "enableLogDetails": true,
        "sortOrder": "Descending",
        "dedupStrategy": "none"
      },
      "title": "Mimic Logs",
      "type": "logs",
      "targets": [
        {
          "expr": "{service=\"mimic\"} | $log_filter",
          "refId": "A"
        }
      ]
    }
  ],
  "refresh": "10s",
  "schemaVersion": 38,
  "style": "dark",
  "tags": ["mimic", "aios"],
  "templating": {
    "list": [
      {
        "current": { "selected": false, "text": "", "value": "" },
        "hide": 0,
        "name": "log_filter",
        "options": [],
        "query": "",
        "skipUrlSync": false,
        "type": "textbox",
        "label": "Log Filter"
      }
    ]
  },
  "time": { "from": "now-1h", "to": "now" },
  "timepicker": {},
  "timezone": "",
  "title": "Mimic",
  "uid": "mimic-overview",
  "version": 1
}
